bfm/__init__.py
bfm/__main__.py
bfm/format.py
bfm/data/IEEE_conference.txt
bfm/data/IEEE_journal.txt
bfm/data/IEEE_magazine.txt
bfm/data/others.txt
bibtex_formatter-1.4.0.dist-info/licenses/LICENSE
bibtex_formatter-1.4.0.dist-info/METADATA
bibtex_formatter-1.4.0.dist-info/WHEEL
bibtex_formatter-1.4.0.dist-info/entry_points.txt
bibtex_formatter-1.4.0.dist-info/top_level.txt
bibtex_formatter-1.4.0.dist-info/RECORD
