Metadata-Version: 2.4
Name: bibtex-formatter
Version: 1.4.0
Summary: Format
Home-page: https://github.com/Nickydusk/BibTeX-Formatter.git
License-File: LICENSE
Requires-Dist: seatable_api
Dynamic: description
Dynamic: description-content-type
Dynamic: home-page
Dynamic: license-file
Dynamic: requires-dist
Dynamic: summary
